links/__init__.py
links/admin.py
links/apps.py
links/migrations/0001_initial.py
links/migrations/0002_url_user_alter_url_token_alter_url_url.py
links/migrations/__init__.py
links/mixins.py
links/models.py
links/templates/links/base.html
links/templates/links/components/delete-modal.html
links/templates/links/components/messages.html
links/templates/links/components/navbar.html
links/templates/links/components/url.html
links/templates/links/create.html
links/templates/links/delete.html
links/templates/links/detail.html
links/templates/links/index.html
links/templates/links/list.html
links/templates/links/update.html
links/templates/registration/logged_out.html
links/templates/registration/login.html
links/tests.py
links/urls.py
links/views.py
django_short_links-0.1.5.dist-info/LICENSE
django_short_links-0.1.5.dist-info/METADATA
django_short_links-0.1.5.dist-info/WHEEL
django_short_links-0.1.5.dist-info/RECORD
