Metadata-Version: 2.1
Name: django-short-links
Version: 0.1.5
Summary: URL shortener Django app
Home-page: https://github.com/youzarsiph/django-short-links/
License: MIT
Author: Yousef Abu Shanab
Author-email: josephyousef249@gmail.com
Requires-Python: >=3.9,<4.0
Classifier: License :: OSI Approved :: MIT License
Classifier: Programming Language :: Python :: 3
Classifier: Programming Language :: Python :: 3.9
Classifier: Programming Language :: Python :: 3.10
Classifier: Programming Language :: Python :: 3.11
Requires-Dist: django (>=4.2,<5.0)
Project-URL: Repository, https://github.com/youzarsiph/django-short-links/
